ai_verge-0.0.1.dist-info/licenses/LICENSE
verge/__init__.py
verge/algorithms/__init__.py
verge/core/__init__.py
verge/core/graph.py
verge/transformers/__init__.py
verge/viz/__init__.py
verge/viz/render.py
ai_verge-0.0.1.dist-info/METADATA
ai_verge-0.0.1.dist-info/WHEEL
ai_verge-0.0.1.dist-info/top_level.txt
ai_verge-0.0.1.dist-info/RECORD
